ignnition/__init__.py
ignnition/_version.py
ignnition/aggregation_classes.py
ignnition/custom_callbacks.py
ignnition/data_generator.py
ignnition/error_handling.py
ignnition/gnn_model.py
ignnition/ignnition_model.py
ignnition/model_classes.py
ignnition/mp_classes.py
ignnition/operation_classes.py
ignnition/schema.json
ignnition/utils.py
ignnition/yaml_preprocessing.py
ignnition-1.7.0.dist-info/LICENSE
ignnition-1.7.0.dist-info/METADATA
ignnition-1.7.0.dist-info/WHEEL
ignnition-1.7.0.dist-info/top_level.txt
ignnition-1.7.0.dist-info/RECORD
