Metadata-Version: 2.1
Name: ignnition
Version: 1.7.0
Summary: Library for fast prototyping of GNN
Home-page: https://ignnition.org/
Author: Barcelona Neural Networking Center
Author-email: ignnition@contactus.net
License: Apache license 2.0
Keywords: Machine Learning,Graph Neural Networks,Networking,Artificial Intelligence
Platform: UNKNOWN
Classifier: Development Status :: 4 - Beta
Classifier: Intended Audience :: Developers
Classifier: Topic :: Software Development :: Build Tools
Classifier: License :: OSI Approved :: Apache Software License
Classifier: Programming Language :: Python :: 3.7
License-File: LICENSE
Requires-Dist: importlib-metadata (==4.6.*)
Requires-Dist: jsonschema (==3.2.*)
Requires-Dist: tensorflow (==2.6.*)
Requires-Dist: networkx (==2.5.*)
Requires-Dist: pyyaml (==5.4.*)
